flask_redmail/__init__.py
flask_redmail/_version.py
flask_redmail/test/__init__.py
flask_redmail/test/conftest.py
flask_redmail/test/test_creation.py
flask_redmail/test/test_legacy.py
flask_redmail/test/test_send.py
Flask_Redmail-0.3.0.dist-info/LICENSE
Flask_Redmail-0.3.0.dist-info/METADATA
Flask_Redmail-0.3.0.dist-info/WHEEL
Flask_Redmail-0.3.0.dist-info/top_level.txt
Flask_Redmail-0.3.0.dist-info/RECORD
